{
    "interactionModel": {
        "languageModel": {
            "invocationName": "entscheidungshilfe",
            "intents": [
                {
                    "name": "AMAZON.FallbackIntent",
                    "samples": []
                },
                {
                    "name": "AMAZON.CancelIntent",
                    "samples": []
                },
                {
                    "name": "AMAZON.HelpIntent",
                    "samples": []
                },
                {
                    "name": "AMAZON.StopIntent",
                    "samples": []
                },
                {
                    "name": "AMAZON.NavigateHomeIntent",
                    "samples": []
                },
                {
                    "name": "DecisionIntent",
                    "slots": [
                        {
                            "name": "message",
                            "type": "AMAZON.SearchQuery"
                        }
                    ],
                    "samples": [
                        "ich {message} darf",
                        "frage entscheidungshilfe ob ich {message} darf",
                        "ob die policy es erlaubt zu {message}",
                        "ob es erlaubt ist {message}",
                        "es erlaubt ist {message}",
                        "ob ich {message} darf",
                        "darf ich {message}",
                        "was sagt die policy zu {message}",
                        "sagt die policy zu {message}",
                        "ist es erlaubt {message}",
                        "ob ich {message}",
                        "ich {message}",
                        "ob es {message}",
                        "es {message}",
                        "wie es aussieht {message}",
                        "es aussieht {message}"
                    ]
                }
            ],
            "types": []
        }
    }
}